maverick/__init__.py
maverick/_registered_players.py
maverick/card.py
maverick/deck.py
maverick/enums.py
maverick/eventbus.py
maverick/events.py
maverick/game.py
maverick/hand.py
maverick/holding.py
maverick/player.py
maverick/playeraction.py
maverick/players/__init__.py
maverick/players/agressivebot.py
maverick/players/archetypes/__init__.py
maverick/players/archetypes/abc.py
maverick/players/archetypes/bully.py
maverick/players/archetypes/fish.py
maverick/players/archetypes/grinder.py
maverick/players/archetypes/gto.py
maverick/players/archetypes/hero_caller.py
maverick/players/archetypes/loose_aggressive.py
maverick/players/archetypes/loose_passive.py
maverick/players/archetypes/maniac.py
maverick/players/archetypes/scared_money.py
maverick/players/archetypes/shark.py
maverick/players/archetypes/tight_agressive.py
maverick/players/archetypes/tight_passive.py
maverick/players/archetypes/tilted.py
maverick/players/archetypes/whale.py
maverick/players/callbot.py
maverick/players/foldbot.py
maverick/playerstate.py
maverick/protocol.py
maverick/rules.py
maverick/state.py
maverick/table.py
maverick/utils/__init__.py
maverick/utils/holding_strength.py
maverick/utils/scoring.py
maverick-0.2.1.dist-info/WHEEL
maverick-0.2.1.dist-info/METADATA
maverick-0.2.1.dist-info/RECORD
