Metadata-Version: 2.3
Name: maverick
Version: 0.2.1
Summary: A Python library for simulating poker games with custom player strategies
Author: Bence Balogh
Author-email: Bence Balogh <benceeok@gmail.com>
License: MIT
Requires-Dist: pydantic>=2.12.5
Requires-Python: >=3.12
Project-URL: Homepage, https://github.com/BALOGHBence/maverick
Project-URL: Documentation, https://pymaverick.readthedocs.io/en/latest/index.html
